[
{"DateTime":"2022/4/19 7:00","Players":"66771","PlayersTrend":"54267.29167","TwitchViewers":"153","GameID":"1203220"},
{"DateTime":"2022/4/19 8:00","Players":"75474","PlayersTrend":"54354.26923","TwitchViewers":"133","GameID":"1203220"},
{"DateTime":"2022/4/19 9:00","Players":"75218","PlayersTrend":"54406.45809","TwitchViewers":"140","GameID":"1203220"},
{"DateTime":"2022/4/19 10:00","Players":"73914","PlayersTrend":"54465.07051","TwitchViewers":"157","GameID":"1203220"},
{"DateTime":"2022/4/19 11:00","Players":"91656","PlayersTrend":"54685.09704","TwitchViewers":"162","GameID":"1203220"},
{"DateTime":"2022/4/19 12:00","Players":"115364","PlayersTrend":"54950.80079","TwitchViewers":"713","GameID":"1203220"},
{"DateTime":"2022/4/19 13:00","Players":"127710","PlayersTrend":"55252.69537","TwitchViewers":"486","GameID":"1203220"},
{"DateTime":"2022/4/19 14:00","Players":"126725","PlayersTrend":"55578.79438","TwitchViewers":"319","GameID":"1203220"},
{"DateTime":"2022/4/19 15:00","Players":"95650","PlayersTrend":"55742.17168","TwitchViewers":"317","GameID":"1203220"},
{"DateTime":"2022/4/19 16:00","Players":"55315","PlayersTrend":"55726.33511","TwitchViewers":"251","GameID":"1203220"},
{"DateTime":"2022/4/19 17:00","Players":"32537","PlayersTrend":"55570.18404","TwitchViewers":"226","GameID":"1203220"},
{"DateTime":"2022/4/19 18:00","Players":"21483","PlayersTrend":"55399.40927","TwitchViewers":"164","GameID":"1203220"},
{"DateTime":"2022/4/19 19:00","Players":"15543","PlayersTrend":"55194.44938","TwitchViewers":"135","GameID":"1203220"},
{"DateTime":"2022/4/19 20:00","Players":"12132","PlayersTrend":"54963.25275","TwitchViewers":"119","GameID":"1203220"},
{"DateTime":"2022/4/19 21:00","Players":"10236","PlayersTrend":"54724.69729","TwitchViewers":"166","GameID":"1203220"},
{"DateTime":"2022/4/19 22:00","Players":"8571","PlayersTrend":"54475.94317","TwitchViewers":"117","GameID":"1203220"},
{"DateTime":"2022/4/19 23:00","Players":"8053","PlayersTrend":"54224.5851","TwitchViewers":"99","GameID":"1203220"},
{"DateTime":"2022/4/20 0:00","Players":"13936","PlayersTrend":"54013.02564","TwitchViewers":"96","GameID":"1203220"},
{"DateTime":"2022/4/20 1:00","Players":"22695","PlayersTrend":"53853.56678","TwitchViewers":"107","GameID":"1203220"},
{"DateTime":"2022/4/20 2:00","Players":"35433","PlayersTrend":"53765.35621","TwitchViewers":"105","GameID":"1203220"},
{"DateTime":"2022/4/20 3:00","Players":"40273","PlayersTrend":"53707.16719","TwitchViewers":"149","GameID":"1203220"},
{"DateTime":"2022/4/20 4:00","Players":"57803","PlayersTrend":"53749.73588","TwitchViewers":"205","GameID":"1203220"},
{"DateTime":"2022/4/20 5:00","Players":"59256","PlayersTrend":"53762.52563","TwitchViewers":"199","GameID":"1203220"},
{"DateTime":"2022/4/20 6:00","Players":"60667","PlayersTrend":"53766.65853","TwitchViewers":"167","GameID":"1203220"},
{"DateTime":"2022/4/20 7:00","Players":"66463","PlayersTrend":"53684.28945","TwitchViewers":"142","GameID":"1203220"},
{"DateTime":"2022/4/20 8:00","Players":"73925","PlayersTrend":"53619.56164","TwitchViewers":"1007","GameID":"1203220"},
{"DateTime":"2022/4/20 9:00","Players":"73850","PlayersTrend":"53586.51282","TwitchViewers":"1868","GameID":"1203220"},
{"DateTime":"2022/4/20 10:00","Players":"74412","PlayersTrend":"53575.75888","TwitchViewers":"1795","GameID":"1203220"},
{"DateTime":"2022/4/20 11:00","Players":"90215","PlayersTrend":"53498.02515","TwitchViewers":"1318","GameID":"1203220"},
{"DateTime":"2022/4/20 12:00","Players":"112976","PlayersTrend":"53425.35774","TwitchViewers":"1180","GameID":"1203220"},
{"DateTime":"2022/4/20 13:00","Players":"125790","PlayersTrend":"53343.11464","TwitchViewers":"1071","GameID":"1203220"},
{"DateTime":"2022/4/20 14:00","Players":"124645","PlayersTrend":"53254.63585","TwitchViewers":"260","GameID":"1203220"},
{"DateTime":"2022/4/20 15:00","Players":"94441","PlayersTrend":"53185.61218","TwitchViewers":"211","GameID":"1203220"},
{"DateTime":"2022/4/20 16:00","Players":"53744","PlayersTrend":"53177.88536","TwitchViewers":"235","GameID":"1203220"},
{"DateTime":"2022/4/20 17:00","Players":"32243","PlayersTrend":"53224.34541","TwitchViewers":"229","GameID":"1203220"},
{"DateTime":"2022/4/20 18:00","Players":"21265","PlayersTrend":"53251.12451","TwitchViewers":"235","GameID":"1203220"},
{"DateTime":"2022/4/20 19:00","Players":"15236","PlayersTrend":"53271.71228","TwitchViewers":"216","GameID":"1203220"},
{"DateTime":"2022/4/20 20:00","Players":"11995","PlayersTrend":"53290.11119","TwitchViewers":"132","GameID":"1203220"},
{"DateTime":"2022/4/20 21:00","Players":"10150","PlayersTrend":"53296.13733","TwitchViewers":"209","GameID":"1203220"},
{"DateTime":"2022/4/20 22:00","Players":"8558","PlayersTrend":"53298.11538","TwitchViewers":"174","GameID":"1203220"},
{"DateTime":"2022/4/20 23:00","Players":"8281","PlayersTrend":"53301.1075","TwitchViewers":"191","GameID":"1203220"},
{"DateTime":"2022/4/21 0:00","Players":"14290","PlayersTrend":"53308.6425","TwitchViewers":"178","GameID":"1203220"},
{"DateTime":"2022/4/21 1:00","Players":"23073","PlayersTrend":"53311.13609","TwitchViewers":"214","GameID":"1203220"},
{"DateTime":"2022/4/21 2:00","Players":"35906","PlayersTrend":"53316.81879","TwitchViewers":"228","GameID":"1203220"},
{"DateTime":"2022/4/21 3:00","Players":"40810","PlayersTrend":"53337.89103","TwitchViewers":"203","GameID":"1203220"},
{"DateTime":"2022/4/21 4:00","Players":"57296","PlayersTrend":"53358.94847","TwitchViewers":"225","GameID":"1203220"},
{"DateTime":"2022/4/21 5:00","Players":"58276","PlayersTrend":"53352.27096","TwitchViewers":"232","GameID":"1203220"},
{"DateTime":"2022/4/21 6:00","Players":"58318","PlayersTrend":"53361.85848","TwitchViewers":"589","GameID":"1203220"},
{"DateTime":"2022/4/21 7:00","Players":"64798","PlayersTrend":"53463.17406","TwitchViewers":"613","GameID":"1203220"},
{"DateTime":"2022/4/21 8:00","Players":"73124","PlayersTrend":"53564.5927","TwitchViewers":"621","GameID":"1203220"},
{"DateTime":"2022/4/21 9:00","Players":"73339","PlayersTrend":"53638.15508","TwitchViewers":"1596","GameID":"1203220"},
{"DateTime":"2022/4/21 10:00","Players":"72345","PlayersTrend":"53691.62377","TwitchViewers":"1690","GameID":"1203220"},
{"DateTime":"2022/4/21 11:00","Players":"88482","PlayersTrend":"53838.16667","TwitchViewers":"751","GameID":"1203220"},
{"DateTime":"2022/4/21 12:00","Players":"110872","PlayersTrend":"54041.79906","TwitchViewers":"1597","GameID":"1203220"},
{"DateTime":"2022/4/21 13:00","Players":"123536","PlayersTrend":"54204.79216","TwitchViewers":"1773","GameID":"1203220"},
{"DateTime":"2022/4/21 14:00","Players":"122761","PlayersTrend":"54282.03674","TwitchViewers":"478","GameID":"1203220"},
{"DateTime":"2022/4/21 15:00","Players":"94463","PlayersTrend":"54384.48299","TwitchViewers":"293","GameID":"1203220"},
{"DateTime":"2022/4/21 16:00","Players":"55096","PlayersTrend":"54771.01208","TwitchViewers":"316","GameID":"1203220"},
{"DateTime":"2022/4/21 17:00","Players":"33004","PlayersTrend":"55279.29684","TwitchViewers":"283","GameID":"1203220"},
{"DateTime":"2022/4/21 18:00","Players":"21876","PlayersTrend":"55679.42678","TwitchViewers":"183","GameID":"1203220"},
{"DateTime":"2022/4/21 19:00","Players":"15746","PlayersTrend":"55933.19822","TwitchViewers":"163","GameID":"1203220"},
{"DateTime":"2022/4/21 20:00","Players":"12117","PlayersTrend":"56076.14324","TwitchViewers":"140","GameID":"1203220"},
{"DateTime":"2022/4/21 21:00","Players":"10127","PlayersTrend":"56153.78279","TwitchViewers":"151","GameID":"1203220"},
{"DateTime":"2022/4/21 22:00","Players":"8492","PlayersTrend":"56195.88264","TwitchViewers":"127","GameID":"1203220"},
{"DateTime":"2022/4/21 23:00","Players":"8314","PlayersTrend":"56218.21598","TwitchViewers":"145","GameID":"1203220"},
{"DateTime":"2022/4/22 0:00","Players":"14149","PlayersTrend":"56215.64103","TwitchViewers":"163","GameID":"1203220"},
{"DateTime":"2022/4/22 1:00","Players":"22994","PlayersTrend":"56212.05942","TwitchViewers":"269","GameID":"1203220"},
{"DateTime":"2022/4/22 2:00","Players":"36295","PlayersTrend":"56290.38708","TwitchViewers":"359","GameID":"1203220"},
{"DateTime":"2022/4/22 3:00","Players":"41575","PlayersTrend":"56425.76455","TwitchViewers":"486","GameID":"1203220"},
{"DateTime":"2022/4/22 4:00","Players":"57344","PlayersTrend":"56610.29758","TwitchViewers":"482","GameID":"1203220"},
{"DateTime":"2022/4/22 5:00","Players":"59409","PlayersTrend":"56807.85577","TwitchViewers":"433","GameID":"1203220"},
{"DateTime":"2022/4/22 6:00","Players":"62312","PlayersTrend":"57362.97781","TwitchViewers":"399","GameID":"1203220"},
{"DateTime":"2022/4/22 7:00","Players":"68537","PlayersTrend":"58033.86267","TwitchViewers":"141","GameID":"1203220"},
{"DateTime":"2022/4/22 8:00","Players":"75868","PlayersTrend":"58620.64818","TwitchViewers":"222","GameID":"1203220"},
{"DateTime":"2022/4/22 9:00","Players":"76120","PlayersTrend":"59044.90533","TwitchViewers":"225","GameID":"1203220"},
{"DateTime":"2022/4/22 10:00","Players":"78287","PlayersTrend":"59453.76183","TwitchViewers":"578","GameID":"1203220"},
{"DateTime":"2022/4/22 11:00","Players":"96722","PlayersTrend":"59611.53008","TwitchViewers":"504","GameID":"1203220"},
{"DateTime":"2022/4/22 12:00","Players":"117929","PlayersTrend":"59560.20143","TwitchViewers":"1326","GameID":"1203220"},
{"DateTime":"2022/4/22 13:00","Players":"127527","PlayersTrend":"59418.10897","TwitchViewers":"1391","GameID":"1203220"},
{"DateTime":"2022/4/22 14:00","Players":"126816","PlayersTrend":"59284.52441","TwitchViewers":"1299","GameID":"1203220"},
{"DateTime":"2022/4/22 15:00","Players":"108201","PlayersTrend":"59350.41494","TwitchViewers":"451","GameID":"1203220"},
{"DateTime":"2022/4/22 16:00","Players":"73815","PlayersTrend":"59539.44576","TwitchViewers":"260","GameID":"1203220"},
{"DateTime":"2022/4/22 17:00","Players":"48142","PlayersTrend":"59682.47781","TwitchViewers":"273","GameID":"1203220"},
{"DateTime":"2022/4/22 18:00","Players":"31890","PlayersTrend":"59754.70907","TwitchViewers":"384","GameID":"1203220"},
{"DateTime":"2022/4/22 19:00","Players":"21993","PlayersTrend":"59800.43762","TwitchViewers":"346","GameID":"1203220"},
{"DateTime":"2022/4/22 20:00","Players":"16087","PlayersTrend":"59827.22017","TwitchViewers":"219","GameID":"1203220"},
{"DateTime":"2022/4/22 21:00","Players":"12838","PlayersTrend":"59845.10404","TwitchViewers":"155","GameID":"1203220"},
{"DateTime":"2022/4/22 22:00","Players":"10432","PlayersTrend":"59853.59862","TwitchViewers":"256","GameID":"1203220"},
{"DateTime":"2022/4/22 23:00","Players":"9428","PlayersTrend":"59849.50394","TwitchViewers":"295","GameID":"1203220"},
{"DateTime":"2022/4/23 0:00","Players":"15208","PlayersTrend":"59840.53279","TwitchViewers":"474","GameID":"1203220"},
{"DateTime":"2022/4/23 1:00","Players":"27025","PlayersTrend":"59880.26381","TwitchViewers":"316","GameID":"1203220"},
{"DateTime":"2022/4/23 2:00","Players":"42436","PlayersTrend":"59931.75962","TwitchViewers":"306","GameID":"1203220"},
{"DateTime":"2022/4/23 3:00","Players":"50312","PlayersTrend":"60017.12648","TwitchViewers":"236","GameID":"1203220"},
{"DateTime":"2022/4/23 4:00","Players":"66023","PlayersTrend":"60089.47658","TwitchViewers":"284","GameID":"1203220"},
{"DateTime":"2022/4/23 5:00","Players":"80968","PlayersTrend":"60462.26677","TwitchViewers":"302","GameID":"1203220"},
{"DateTime":"2022/4/23 6:00","Players":"89263","PlayersTrend":"60902.52885","TwitchViewers":"289","GameID":"1203220"},
{"DateTime":"2022/4/23 7:00","Players":"93175","PlayersTrend":"61273.88141","TwitchViewers":"240","GameID":"1203220"},
{"DateTime":"2022/4/23 8:00","Players":"93999","PlayersTrend":"61514.52564","TwitchViewers":"232","GameID":"1203220"},
{"DateTime":"2022/4/23 9:00","Players":"91391","PlayersTrend":"61707.51824","TwitchViewers":"222","GameID":"1203220"},
{"DateTime":"2022/4/23 10:00","Players":"80930","PlayersTrend":"61627.03649","TwitchViewers":"199","GameID":"1203220"},
{"DateTime":"2022/4/23 11:00","Players":"91015","PlayersTrend":"61374.59739","TwitchViewers":"1431","GameID":"1203220"},
{"DateTime":"2022/4/23 12:00","Players":"110524","PlayersTrend":"61160.87525","TwitchViewers":"1303","GameID":"1203220"},
{"DateTime":"2022/4/23 13:00","Players":"120196","PlayersTrend":"60979.59147","TwitchViewers":"344","GameID":"1203220"},
{"DateTime":"2022/4/23 14:00","Players":"119616","PlayersTrend":"60801.11662","TwitchViewers":"338","GameID":"1203220"},
{"DateTime":"2022/4/23 15:00","Players":"101616","PlayersTrend":"60623.36859","TwitchViewers":"271","GameID":"1203220"},
{"DateTime":"2022/4/23 16:00","Players":"67879","PlayersTrend":"60279.0498","TwitchViewers":"246","GameID":"1203220"},
{"DateTime":"2022/4/23 17:00","Players":"43322","PlayersTrend":"59925.51652","TwitchViewers":"210","GameID":"1203220"},
{"DateTime":"2022/4/23 18:00","Players":"29179","PlayersTrend":"59701.7251","TwitchViewers":"280","GameID":"1203220"},
{"DateTime":"2022/4/23 19:00","Players":"20458","PlayersTrend":"59572.18343","TwitchViewers":"340","GameID":"1203220"},
{"DateTime":"2022/4/23 20:00","Players":"15289","PlayersTrend":"59513.88018","TwitchViewers":"264","GameID":"1203220"},
{"DateTime":"2022/4/23 21:00","Players":"12308","PlayersTrend":"59493.26578","TwitchViewers":"208","GameID":"1203220"},
{"DateTime":"2022/4/23 22:00","Players":"10108","PlayersTrend":"59496.07396","TwitchViewers":"380","GameID":"1203220"},
{"DateTime":"2022/4/23 23:00","Players":"8882","PlayersTrend":"59500.16963","TwitchViewers":"319","GameID":"1203220"},
{"DateTime":"2022/4/24 0:00","Players":"13736","PlayersTrend":"59489.35947","TwitchViewers":"199","GameID":"1203220"},
{"DateTime":"2022/4/24 1:00","Players":"23562","PlayersTrend":"59429.07372","TwitchViewers":"383","GameID":"1203220"},
{"DateTime":"2022/4/24 2:00","Players":"37406","PlayersTrend":"59296.09443","TwitchViewers":"491","GameID":"1203220"},
{"DateTime":"2022/4/24 3:00","Players":"44296","PlayersTrend":"59107.93245","TwitchViewers":"578","GameID":"1203220"},
{"DateTime":"2022/4/24 4:00","Players":"59720","PlayersTrend":"58883.14744","TwitchViewers":"697","GameID":"1203220"},
{"DateTime":"2022/4/24 5:00","Players":"70688","PlayersTrend":"58535.01824","TwitchViewers":"205","GameID":"1203220"},
{"DateTime":"2022/4/24 6:00","Players":"77176","PlayersTrend":"57999.88881","TwitchViewers":"214","GameID":"1203220"},
{"DateTime":"2022/4/24 7:00","Players":"81471","PlayersTrend":"57409.26627","TwitchViewers":"212","GameID":"1203220"},
{"DateTime":"2022/4/24 8:00","Players":"82680","PlayersTrend":"56866.49507","TwitchViewers":"187","GameID":"1203220"},
{"DateTime":"2022/4/24 9:00","Players":"81326","PlayersTrend":"56452.92086","TwitchViewers":"255","GameID":"1203220"},
{"DateTime":"2022/4/24 10:00","Players":"72490","PlayersTrend":"56106.56386","TwitchViewers":"287","GameID":"1203220"},
{"DateTime":"2022/4/24 11:00","Players":"87326","PlayersTrend":"56029.92258","TwitchViewers":"277","GameID":"1203220"},
{"DateTime":"2022/4/24 12:00","Players":"108797","PlayersTrend":"56024.95143","TwitchViewers":"293","GameID":"1203220"},
{"DateTime":"2022/4/24 13:00","Players":"118607","PlayersTrend":"56012.71721","TwitchViewers":"503","GameID":"1203220"},
{"DateTime":"2022/4/24 14:00","Players":"117261","PlayersTrend":"55982.05547","TwitchViewers":"441","GameID":"1203220"},
{"DateTime":"2022/4/24 15:00","Players":"87772","PlayersTrend":"55587.71351","TwitchViewers":"425","GameID":"1203220"},
{"DateTime":"2022/4/24 16:00","Players":"51313","PlayersTrend":"55095.96573","TwitchViewers":"441","GameID":"1203220"},
{"DateTime":"2022/4/24 17:00","Players":"31225","PlayersTrend":"54736.11538","TwitchViewers":"417","GameID":"1203220"},
{"DateTime":"2022/4/24 18:00","Players":"20959","PlayersTrend":"54490.91716","TwitchViewers":"384","GameID":"1203220"},
{"DateTime":"2022/4/24 19:00","Players":"15492","PlayersTrend":"54353.27761","TwitchViewers":"326","GameID":"1203220"},
{"DateTime":"2022/4/24 20:00","Players":"12273","PlayersTrend":"54277.23619","TwitchViewers":"241","GameID":"1203220"},
{"DateTime":"2022/4/24 21:00","Players":"10450","PlayersTrend":"54238.0175","TwitchViewers":"190","GameID":"1203220"},
{"DateTime":"2022/4/24 22:00","Players":"8724","PlayersTrend":"54213.91913","TwitchViewers":"420","GameID":"1203220"},
{"DateTime":"2022/4/24 23:00","Players":"8257","PlayersTrend":"54217.14892","TwitchViewers":"404","GameID":"1203220"},
{"DateTime":"2022/4/25 0:00","Players":"13620","PlayersTrend":"54235.93762","TwitchViewers":"294","GameID":"1203220"},
{"DateTime":"2022/4/25 1:00","Players":"21447","PlayersTrend":"54185.25222","TwitchViewers":"198","GameID":"1203220"},
{"DateTime":"2022/4/25 2:00","Players":"33336","PlayersTrend":"54068.46746","TwitchViewers":"197","GameID":"1203220"},
{"DateTime":"2022/4/25 3:00","Players":"38090","PlayersTrend":"53875.54882","TwitchViewers":"178","GameID":"1203220"},
{"DateTime":"2022/4/25 4:00","Players":"52910","PlayersTrend":"53653.95316","TwitchViewers":"91","GameID":"1203220"},
{"DateTime":"2022/4/25 5:00","Players":"53148","PlayersTrend":"53052.04635","TwitchViewers":"92","GameID":"1203220"},
{"DateTime":"2022/4/25 6:00","Players":"53882","PlayersTrend":"52248.98077","TwitchViewers":"183","GameID":"1203220"},
{"DateTime":"2022/4/25 7:00","Players":"60767","PlayersTrend":"51529.0466","TwitchViewers":"150","GameID":"1203220"},
{"DateTime":"2022/4/25 8:00","Players":"69471","PlayersTrend":"51027.78674","TwitchViewers":"243","GameID":"1203220"},
{"DateTime":"2022/4/25 9:00","Players":"69562","PlayersTrend":"50496.25197","TwitchViewers":"256","GameID":"1203220"},
{"DateTime":"2022/4/25 10:00","Players":"71797","PlayersTrend":"50359.61982","TwitchViewers":"255","GameID":"1203220"},
{"DateTime":"2022/4/25 11:00","Players":"87802","PlayersTrend":"50252.07692","TwitchViewers":"332","GameID":"1203220"},
{"DateTime":"2022/4/25 12:00","Players":"108286","PlayersTrend":"50013.80646","TwitchViewers":"855","GameID":"1203220"},
{"DateTime":"2022/4/25 13:00","Players":"118684","PlayersTrend":"49675.82249","TwitchViewers":"798","GameID":"1203220"},
{"DateTime":"2022/4/25 14:00","Players":"117347","PlayersTrend":"49276.68491","TwitchViewers":"623","GameID":"1203220"},
{"DateTime":"2022/4/25 15:00","Players":"87456","PlayersTrend":"48870.4359","TwitchViewers":"544","GameID":"1203220"},
{"DateTime":"2022/4/25 16:00","Players":"50651","PlayersTrend":"48627.84911","TwitchViewers":"501","GameID":"1203220"},
{"DateTime":"2022/4/25 17:00","Players":"30037","PlayersTrend":"48582.74556","TwitchViewers":"334","GameID":"1203220"},
{"DateTime":"2022/4/25 18:00","Players":"20333","PlayersTrend":"48680.50937","TwitchViewers":"326","GameID":"1203220"},
{"DateTime":"2022/4/25 19:00","Players":"14843","PlayersTrend":"48834.5","TwitchViewers":"314","GameID":"1203220"},
{"DateTime":"2022/4/25 20:00","Players":"11593","PlayersTrend":"49019.45587","TwitchViewers":"177","GameID":"1203220"},
{"DateTime":"2022/4/25 21:00","Players":"9761","PlayersTrend":"49222.95661","TwitchViewers":"373","GameID":"1203220"},
{"DateTime":"2022/4/25 22:00","Players":"8308","PlayersTrend":"49447.65976","TwitchViewers":"327","GameID":"1203220"},
{"DateTime":"2022/4/25 23:00","Players":"7647","PlayersTrend":"49673.10256","TwitchViewers":"488","GameID":"1203220"},
{"DateTime":"2022/4/26 0:00","Players":"12787","PlayersTrend":"49893.30399","TwitchViewers":"438","GameID":"1203220"},
{"DateTime":"2022/4/26 1:00","Players":"20821","PlayersTrend":"50090.94822","TwitchViewers":"234","GameID":"1203220"},
{"DateTime":"2022/4/26 2:00","Players":"32611","PlayersTrend":"50236.76677","TwitchViewers":"361","GameID":"1203220"},
{"DateTime":"2022/4/26 3:00","Players":"36644","PlayersTrend":"50283.31164","TwitchViewers":"378","GameID":"1203220"},
{"DateTime":"2022/4/26 4:00","Players":"51162","PlayersTrend":"50292.99408","TwitchViewers":"12658","GameID":"1203220"},
{"DateTime":"2022/4/26 5:00","Players":"52881","PlayersTrend":"50276.52219","TwitchViewers":"14307","GameID":"1203220"},
{"DateTime":"2022/4/26 6:00","Players":"54026","PlayersTrend":"50266.66938","TwitchViewers":"14783","GameID":"1203220"},
{"DateTime":"2022/4/26 7:00","Players":"54322","PlayersTrend":"49977.19527","TwitchViewers":"723","GameID":"1203220"}
]
